odoo8_addon_l10n_br_stock_account-8.0.1.0.1.99.dev29-py2.7-nspkg.pth
odoo8_addon_l10n_br_stock_account-8.0.1.0.1.99.dev29.dist-info/METADATA
odoo8_addon_l10n_br_stock_account-8.0.1.0.1.99.dev29.dist-info/RECORD
odoo8_addon_l10n_br_stock_account-8.0.1.0.1.99.dev29.dist-info/WHEEL
odoo8_addon_l10n_br_stock_account-8.0.1.0.1.99.dev29.dist-info/namespace_packages.txt
odoo8_addon_l10n_br_stock_account-8.0.1.0.1.99.dev29.dist-info/top_level.txt
odoo_addons/l10n_br_stock_account/README.rst
odoo_addons/l10n_br_stock_account/__init__.py
odoo_addons/l10n_br_stock_account/__openerp__.py
odoo_addons/l10n_br_stock_account/data/l10n_br_stock_account_data.xml
odoo_addons/l10n_br_stock_account/i18n/pt_BR.po
odoo_addons/l10n_br_stock_account/models/__init__.py
odoo_addons/l10n_br_stock_account/models/procurement.py
odoo_addons/l10n_br_stock_account/models/res_company.py
odoo_addons/l10n_br_stock_account/models/stock.py
odoo_addons/l10n_br_stock_account/models/stock_account.py
odoo_addons/l10n_br_stock_account/security/ir.model.access.csv
odoo_addons/l10n_br_stock_account/static/description/icon.png
odoo_addons/l10n_br_stock_account/test/stock_internal_picking.yml
odoo_addons/l10n_br_stock_account/test/stock_return_internal_picking.yml
odoo_addons/l10n_br_stock_account/views/res_company_view.xml
odoo_addons/l10n_br_stock_account/views/stock_account_view.xml
odoo_addons/l10n_br_stock_account/views/stock_view.xml
odoo_addons/l10n_br_stock_account/wizard/__init__.py
odoo_addons/l10n_br_stock_account/wizard/stock_invoice_onshipping.py
odoo_addons/l10n_br_stock_account/wizard/stock_invoice_onshipping_view.xml
odoo_addons/l10n_br_stock_account/wizard/stock_return_picking.py
